Models/Multistep_Models.py
Models/Multivariate_Input_Models.py
Models/Multivariate_Input_Multistep_Models.py
Models/Multivariate_Parallel_Models.py
Models/Multivariate_Parallel_Multistep_Models.py
Models/Univariate_Models.py
Models/__init__.py
Models/data_prep.py
Models/timeseries_to_supervised.py
Foercasting_Models-0.0.1.dist-info/LICENSE
Foercasting_Models-0.0.1.dist-info/METADATA
Foercasting_Models-0.0.1.dist-info/WHEEL
Foercasting_Models-0.0.1.dist-info/top_level.txt
Foercasting_Models-0.0.1.dist-info/RECORD
