Metadata-Version: 2.1
Name: Foercasting-Models
Version: 0.0.1
Summary: Prediction models in timeseries
Home-page: https://github.com/IntElligence0?tab=repositories
Author: Abd_Elrahman Basala
Author-email: Abdoubasala2001@gmail.com
Classifier: Programming Language :: Python :: 3
Classifier: License :: OSI Approved :: MIT License
Classifier: Operating System :: OS Independent
Requires-Python: >=3.7
License-File: LICENSE
